Explain_LISA_CNN_test_4/ExplainLISA.py
Explain_LISA_CNN_test_4/Explanations.py
Explain_LISA_CNN_test_4/__init__.py
Explain_LISA_CNN_test_4-0.0.1.dist-info/LICENSE
Explain_LISA_CNN_test_4-0.0.1.dist-info/METADATA
Explain_LISA_CNN_test_4-0.0.1.dist-info/WHEEL
Explain_LISA_CNN_test_4-0.0.1.dist-info/top_level.txt
Explain_LISA_CNN_test_4-0.0.1.dist-info/RECORD
