Metadata-Version: 2.1
Name: Explain-LISA-CNN-test-4
Version: 0.0.1
Summary: Unified Explanation Provider For CNNs
Home-page: UNKNOWN
Author: Sudil H.P Abeyagunasekera
Author-email: <sudilhasithaa51@gmail.com>
License: UNKNOWN
Keywords: LIME,Integrated gradients,SHAP,Anchors,Explainable AI,XAI,CNN Explainer
Platform: UNKNOWN
Classifier: Development Status :: 1 - Planning
Classifier: Intended Audience :: Developers
Classifier: Programming Language :: Python :: 3
Classifier: Operating System :: Unix
Classifier: Operating System :: MacOS :: MacOS X
Classifier: Operating System :: Microsoft :: Windows
License-File: LICENSE
Requires-Dist: opencv-python
Requires-Dist: tensorflow
Requires-Dist: numpy
Requires-Dist: pandas
Requires-Dist: matplotlib
Requires-Dist: alibi
Requires-Dist: lime
Requires-Dist: shap
Requires-Dist: scikit-image
